scrapy_xls/__init__.py
scrapy_xls/xls_spider.py
scrapy_xls-0.0.1.dist-info/LICENSE
scrapy_xls-0.0.1.dist-info/METADATA
scrapy_xls-0.0.1.dist-info/WHEEL
scrapy_xls-0.0.1.dist-info/top_level.txt
scrapy_xls-0.0.1.dist-info/RECORD
