Metadata-Version: 2.1
Name: scrapy-xls
Version: 0.0.1
Summary: Scrapy spider for parsing XLS files.
Home-page: https://github.com/kennyaires/scrapy-xls
Author: Kenny
Requires-Python: >=3.6
License-File: LICENSE
Requires-Dist: scrapy
Requires-Dist: pandas
Requires-Dist: openpyxl
